Workbook

Sheet Rubriques
A1: Rubriques | B1: COMPTE | C1: Chapitre | D1: Solde
A2: Charges_int_epargne | B2: 601610000 | C2: 601610000 INT SUR DEPOT A TERME INST | D2: =IF(B2="","",IFERROR(INDEX(Balance!$E$2:$E$800,MATCH(B2,Balance!$A$2:$A$800,0)),"Non trouvé")) -> -118247811
A3: Charges_int_epargne | B3: 602511000 | C3: 602511000 INTERETS SUR DEPOTS A VUE | D3: =IF(B3="","",IFERROR(INDEX(Balance!$E$2:$E$800,MATCH(B3,Balance!$A$2:$A$800,0)),"Non trouvé")) -> -2033
A4: Charges_int_epargne | B4: 602520000 | C4: 602520000 INTERETS EPARGNE PROJET | D4: =IF(B4="","",IFERROR(INDEX(Balance!$E$2:$E$800,MATCH(B4,Balance!$A$2:$A$800,0)),"Non trouvé")) -> -13362857
A5: Charges_int_epargne | B5: 602521000 | C5: 602521000 INTERETS CAT DEE 3 À 6 MOIS | D5: =IF(B5="","",IFERROR(INDEX(Balance!$E$2:$E$800,MATCH(B5,Balance!$A$2:$A$800,0)),"Non trouvé")) -> -3000483
A6: Charges_int_epargne | B6: 602522000 | C6: 602522000 INTERETS CAT DE 6 A 12 MOIS | D6: =IF(B6="","",IFERROR(INDEX(Balance!$E$2:$E$800,MATCH(B6,Balance!$A$2:$A$800,0)),"Non trouvé")) -> -11068326
A7: Charges_int_epargne | B7: 602523000 | C7: 602523000 INTETETS CAT PLUS DE 12 MOI | D7: =IF(B7="","",IFERROR(INDEX(Balance!$E$2:$E$800,MATCH(B7,Balance!$A$2:$A$800,0)),"Non trouvé")) -> -46250353
A8: Charges_int_epargne | B8: 602524000 | C8: 602524000 INTERETS DAT INSTITUTIONNE | D8: =IF(B8="","",IFERROR(INDEX(Balance!$E$2:$E$800,MATCH(B8,Balance!$A$2:$A$800,0)),"Non trouvé")) -> -176016986
A9: Charges_int_epargne | B9: 602531000 | C9: 602531000 INTERETS EPARGNE SPECIALE | D9: =IF(B9="","",IFERROR(INDEX(Balance!$E$2:$E$800,MATCH(B9,Balance!$A$2:$A$800,0)),"Non trouvé")) -> -173815496
A11: charges_financieres | B11: 601750000 | C11: 601750000 INTERETS EMPRUNTS C.T. | D11: =IF(B11="","",IFERROR(INDEX(Balance!$E$2:$E$800,MATCH(B11,Balance!$A$2:$A$800,0)),"Non trouvé")) -> 0
A12: charges_financieres | B12: 601780000 | C12: 601780000 INTERETS EMPRUNTS A TERME | D12: =IF(B12="","",IFERROR(INDEX(Balance!$E$2:$E$800,MATCH(B12,Balance!$A$2:$A$800,0)),"Non trouvé")) -> -2824459039
A13: charges_financieres | B13: 601781000 | C13: 601781000 INTERETS SUR EMPRUNTS A T | D13: =IF(B13="","",IFERROR(INDEX(Balance!$E$2:$E$800,MATCH(B13,Balance!$A$2:$A$800,0)),"Non trouvé")) -> -985339
A14: charges_financieres | B14: 601900000 | C14: 601900000 COMMISSIONS PAYEES | D14: =IF(B14="","",IFERROR(INDEX(Balance!$E$2:$E$800,MATCH(B14,Balance!$A$2:$A$800,0)),"Non trouvé")) -> -213973114
... A184: recuperation_pertes_et_creances_amorties | B184: 772300000 | C184: 772300000 PROFITS EXCEPTIONNELS | D184: =IF(B184="","",IFERROR(INDEX(Balance!$E$2:$E$800,MATCH(B184,Balance!$A$2:$A$800,0)),"Non trouvé")) -> 20816927

Sheet Balance
A1: COMPTE | B1: LIBELLE | C1: SOLDE_CUMULE_DEBIT | D1: SOLDE_CUMULE_CREDIT | E1: SOLDE
A2: 49999999 | B2: COMPTE D'EQUILIBRE IMPORT | E2: =D2-C2 -> 0
A3: 101110126 | B3: CAISSE DAKAR | D3: 1 | E3: =D3-C3 -> 1
A4: 101110201 | B4: PETITE CAISSE KAOLACK | E4: =D4-C4 -> 0
A5: 101110202 | B5: CAISSE UNITE 4 | C5: 50936815 | E5: =D5-C5 -> -50936815
A6: 101110207 | B6: CAISSE MBIRKILANE | C6: 1704275 | E6: =D6-C6 -> -1704275
A7: 101110208 | B7: CAISSE NDORONG | E7: =D7-C7 -> 0
A8: 101110209 | B8: CAISSE GUINGUINEO | C8: 1921000 | E8: =D8-C8 -> -1921000
A9: 101110215 | B9: CAISSE DIEUPPEUL | C9: 14718340 | E9: =D9-C9 -> -14718340
A10: 101110216 | B10: CAISSE PATTE D'OIE | E10: =D10-C10 -> 0
A11: 101110301 | B11: PETITE CAISSE ZIGUINCHOR | E11: =D11-C11 -> 0
A12: 101110302 | B12: CAISSE YARAKH | E12: =D12-C12 -> 0
A13: 101110401 | B13: PETITE CAISSE KOLDA | E13: =D13-C13 -> 0
A14: 101110502 | B14: PETITE CAISSE LOUGA | E14: =D14-C14 -> 0
A15: 101110601 | B15: PETITE CAISSE DIOURBEL | E15: =D15-C15 -> 0
A16: 101110701 | B16: PETITE CAISSE OURO | E16: =D16-C16 -> 0
A17: 101110801 | B17: PETITE CAISSE TAMBA | E17: =D17-C17 -> 0
A18: 101110901 | B18: PETITE CAISSE SAINT LOUIS | E18: =D18-C18 -> 0
A19: 101110902 | B19: PETITE CAISSE THIES | E19: =D19-C19 -> 0
A20: 101110903 | B20: CAISSE MEKHE | C20: 10657300 | E20: =D20-C20 -> -10657300
A21: 101110905 | B21: CAISSE SANTHIABA | E21: =D21-C21 -> 0
A22: 101111201 | B22: PETITE CAISSE MBOUR | E22: =D22-C22 -> 0
A23: 101111202 | B23: CAISSE 11 NOVEMBRE | C23: 5766165 | E23: =D23-C23 -> -5766165
A24: 101111301 | B24: PETITE CAISSE TOUBA | E24: =D24-C24 -> 0
A25: 101111302 | B25: PETITE CAISSE TOUBA | E25: =D25-C25 -> 0
A26: 101111503 | B26: PETITE CAISSE PLATEAU | E26: =D26-C26 -> 0
A27: 101111903 | B27: CAISSE THIES RTE DE MBOUR | C27: 2196205 | E27: =D27-C27 -> -2196205
A28: 101111905 | B28: CAISSE NGALLELE STLOUIS | C28: 1177090 | E28: =D28-C28 -> -1177090
A29: 101120112 | B29: CAISSE COLOBANE | C29: 19090485 | E29: =D29-C29 -> -19090485
A30: 101120116 | B30: CAISSE MEDINA | E30: =D30-C30 -> 0
A31: 101120117 | B31: CAISSE SANDAGA | C31: 12524170 | E31: =D31-C31 -> -12524170
A32: 101120118 | B32: CAISSE MEDINA RUE 9 | C32: 58357910 | E32: =D32-C32 -> -58357910
A33: 101120125 | B33: CAISSE DALIFORT | C33: 11439400 | E33: =D33-C33 -> -11439400
A34: 101120129 | B34: CAISSE YOFF | C34: 9349025 | E34: =D34-C34 -> -9349025
A35: 101120140 | B35: CAISSE HLM | C35: 8168935 | E35: =D35-C35 -> -8168935
A36: 101120150 | B36: CAISSE OUAKAM | C36: 4837325 | E36: =D36-C36 -> -4837325
A37: 101120203 | B37: CAISSE KAFFRINE | C37: 102789223 | E37: =D37-C37 -> -102789223
A38: 101120204 | B38: CAISSE FATICK | C38: 3896305 | E38: =D38-C38 -> -3896305
A39: 101120205 | B39: CAISSE PASSY | C39: 3061100 | E39: =D39-C39 -> -3061100
A40: 101120206 | B40: CAISSE KOUNGHEUL | C40: 33157365 | E40: =D40-C40 -> -33157365
A41: 101120211 | B41: CAISSE KAOLACK NORD | C41: 57777590 | E41: =D41-C41 -> -57777590
A42: 101120212 | B42: CAISSE NIORO | C42: 9107420 | E42: =D42-C42 -> -9107420
A43: 101120216 | B43: CAISSE MEDINA 2 | E43: =D43-C43 -> 0
A44: 101120303 | B44: CAISSE BIGNONA | C44: 3700785 | E44: =D44-C44 -> -3700785
A45: 101120403 | B45: CAISSE VELINGARA | E45: =D45-C45 -> 0
A46: 101120404 | B46: CAISSE SEDHIOU | C46: 5826925 | E46: =D46-C46 -> -5826925
A47: 101120405 | B47: CAISSE DIAOBE | C47: 1109000 | E47: =D47-C47 -> -1109000
A48: 101120502 | B48: CAISSE RICHARD TOLL | C48: 18494285 | E48: =D48-C48 -> -18494285
A49: 101120503 | B49: CAISSE LOUGA | C49: 77381456 | E49: =D49-C49 -> -77381456
A50: 101120511 | B50: CAISSE SAINT LOUIS 2 | C50: 607250 | E50: =D50-C50 -> -607250
A51: 101120513 | B51: CAISSE KEBEMER | C51: 4946990 | E51: =D51-C51 -> -4946990
A52: 101120515 | B52: CAISSE DAHRA | C52: 16231370 | E52: =D52-C52 -> -16231370
A53: 101120516 | B53: CAISSE NIOMRE | C53: 7767895 | E53: =D53-C53 -> -7767895
A54: 101120607 | B54: CAISSE BAMBEY | C54: 8198850 | E54: =D54-C54 -> -8198850
A55: 101120707 | B55: CAISSE NDIOUM | C55: 9499580 | E55: =D55-C55 -> -9499580
A56: 101120708 | B56: CAISSE GALOYA | C56: 823565 | E56: =D56-C56 -> -823565
A57: 101120803 | B57: CAISSE KEDOUGOU | C57: 5234415 | E57: =D57-C57 -> -5234415
... A65: 101120909 | B65: CAISSE HERSENT | C65: 1469900 | E65: =D65-C65 -> -1469900
A66: 101120910 | B66: CAISSE MARCHE THIES | E66: =D66-C66 -> 0
A67: 101120911 | B67: CAISSE MBORO | C67: 954100 | E67: =D67-C67 -> -954100
A68: 101121009 | B68: CAISSE KEUR MASSAR | E68: =D68-C68 -> 0
A69: 101121010 | B69: CAISSE KEUR MASSAR 2 | C69: 12272745 | E69: =D69-C69 -> -12272745
A70: 101121011 | B70: CAISSE KEUR MASSAR | E70: =D70-C70 -> 0
A71: 101121014 | B71: CAISSE RUFISQUE | C71: 10223314 | E71: =D71-C71 -> -10223314
A72: 101121015 | B72: CAISSE BAYAKH | C72: 10406360 | E72: =D72-C72 -> -10406360
A73: 101121016 | B73: CAISSE DIAMNIADIO | C73: 718000 | E73: =D73-C73 -> -718000
A74: 101121017 | B74: CAISSE RUFISQUE 3 | C74: 189173345 | E74: =D74-C74 -> -189173345
A75: 101121031 | B75: CAISSE POSTE THIAROYE | C75: 9898080 | E75: =D75-C75 -> -9898080
A76: 101121036 | B76: CAISSE YEUMBEUL | C76: 3309485 | E76: =D76-C76 -> -3309485
A77: 101121041 | B77: CAISSE GUEDIAWAYE | C77: 10526535 | E77: =D77-C77 -> -10526535
A78: 101121116 | B78: CAISSE GUEDIAWAYE 3 | C78: 5008375 | E78: =D78-C78 -> -5008375
A79: 101121206 | B79: CAISSE NGUEKOKH | C79: 1149680 | E79: =D79-C79 -> -1149680
A80: 101121207 | B80: CAISSE MARCHE CENTRAL MB | C80: 20739555 | E80: =D80-C80 -> -20739555
A81: 101121208 | B81: CAISSE JOAL | C81: 23005425 | E81: =D81-C81 -> -23005425
A82: 101121216 | B82: CAISSE PIKINE CHAVANNEL | C82: 9698125 | E82: =D82-C82 -> -9698125
A83: 101121304 | B83: CAISSE MBACKE | C83: 2298250 | E83: =D83-C83 -> -2298250
A84: 101121305 | B84: CAISSE TOUBA | E84: =D84-C84 -> 0
A85: 101121306 | B85: CAISSE MARCHE OCAS | C85: 1608075 | E85: =D85-C85 -> -1608075
A86: 101121307 | B86: CAISSE DAROU MOUSTY | E86: =D86-C86 -> 0
A87: 101121416 | B87: CAISSE GRAND-YOFF | C87: 15560340 | E87: =D87-C87 -> -15560340
A88: 101121418 | B88: CAISSE THIAROYE | C88: 6510565 | E88: =D88-C88 -> -6510565
A89: 101121427 | B89: CAISSE UNITE 20 | C89: 4518585 | E89: =D89-C89 -> -4518585
A90: 101121433 | B90: CAISSE PARCELLES ASSAINIES | C90: 81320370 | E90: =D90-C90 -> -81320370
A91: 101121434 | B91: CAISSE SCAT URBAM | C91: 7925007 | E91: =D91-C91 -> -7925007
A92: 101121435 | B92: CAISSE MARISTE | C92: 11473775 | E92: =D92-C92 -> -11473775
A93: 101121441 | B93: CAISSE UNITE 12 | C93: 47111200 | E93: =D93-C93 -> -47111200
A94: 101121442 | B94: CAISSE UNITE4 GOLF | C94: 3637220 | E94: =D94-C94 -> -3637220
A95: 101121502 | B95: CAISSE PRINCIPALE PLATEAU | E95: =D95-C95 -> 0
A96: 101121503 | B96: CAISSE REGUL DAKAR PLATEA | E96: =D96-C96 -> 0
A97: 101121515 | B97: CAISSE LOUGA 2 | C97: 6967520 | E97: =D97-C97 -> -6967520
A98: 101122116 | B98: CAISSE GUEDIAWAYE 2 | C98: 1909290 | E98: =D98-C98 -> -1909290
A99: 101130124 | B99: CAISSE PRINCIPALE DAKAR | C99: 40925184 | E99: =D99-C99 -> -40925184
A100: 101130125 | B100: CAISSE PRINCIPAL SIEGE | C100: 197739000 | E100: =D100-C100 -> -197739000
A101: 101130201 | B101: CAISSE PRINCIPALE KAOLACK | C101: 147419905 | E101: =D101-C101 -> -147419905
A102: 101130206 | B102: CAISSE REGUL KK | E102: =D102-C102 -> 0
A103: 101130207 | B103: CAISSE REGUL KAFFRINE | C103: 1 | E103: =D103-C103 -> -1
A104: 101130301 | B104: CAISSE ZIG | C104: 36898040 | E104: =D104-C104 -> -36898040
A105: 101130302 | B105: CAISSE REGUL ZIGUINCHOR | E105: =D105-C105 -> 0
A106: 101130303 | B106: CAISSE BOUCOTT | C106: 7994625 | E106: =D106-C106 -> -7994625
A107: 101130304 | B107: CAISSE CAP SKIRING | C107: 1831740 | E107: =D107-C107 -> -1831740
...
